cleanclassify/__init__.py
cleanclassify/__main__.py
cleanclassify/classify.py
cleanclassify/cleaner.py
cleanclassify/gui.py
cleanclassify-0.1.dist-info/licenses/LICENSE
cleanclassify-0.1.dist-info/METADATA
cleanclassify-0.1.dist-info/WHEEL
cleanclassify-0.1.dist-info/entry_points.txt
cleanclassify-0.1.dist-info/top_level.txt
cleanclassify-0.1.dist-info/RECORD
