Metadata-Version: 2.4
Name: cleanclassify
Version: 0.1
Summary: A beginner-friendly Python Package to clean, classify, and visualize CSV data via a simple GUI.
Home-page: https://github.com/SafaMahveen/cleanclassify.git
Author: Safa Mahveen
Author-email: thesafamahveen@gmail.com
License: MIT
Keywords: machine-learning tkinter gui classification sklearn pandas csv
Requires-Python: >=3.8
License-File: LICENSE
Requires-Dist: pandas>=2.3.0
Requires-Dist: numpy>=2.3.1
Requires-Dist: matplotlib>=3.10.3
Requires-Dist: scikit-learn>=1.7.0
Dynamic: author
Dynamic: author-email
Dynamic: description
Dynamic: description-content-type
Dynamic: home-page
Dynamic: keywords
Dynamic: license
Dynamic: license-file
Dynamic: requires-dist
Dynamic: requires-python
Dynamic: summary
